AugmentedDataLoader/__init__.py
AugmentedDataLoader/datasets/ImageToImageDataset.py
AugmentedDataLoader/datasets/__init__.py
AugmentedDataLoader/loaders/AugmentedDataLoader.py
AugmentedDataLoader/loaders/AugmentedImageToImageDataLoader.py
AugmentedDataLoader/loaders/BaseAugmentedDataLoader.py
AugmentedDataLoader/loaders/__init__.py
AugmentedDataLoader/tests/AugmentedDataLoaderTest.py
AugmentedDataLoader/tests/__init__.py
AugmentedDataLoader/utils/AugmentedDataLoaderUtils.py
AugmentedDataLoader/utils/__init__.py
augmenteddataloader-3.0.5.dist-info/licenses/LICENSE.txt
augmenteddataloader-3.0.5.dist-info/METADATA
augmenteddataloader-3.0.5.dist-info/WHEEL
augmenteddataloader-3.0.5.dist-info/top_level.txt
augmenteddataloader-3.0.5.dist-info/RECORD
