Metadata-Version: 2.4
Name: AugmentedDataLoader
Version: 3.0.5
Summary: Medical image augmentation tool integrated with PyTorch & MONAI.
Home-page: https://github.com/ciroraggio/AugmentedDataLoader
Author: Ciro B. Raggio, P. Zaffino
Author-email: Ciro Benito Raggio <ciro.raggio@kit.edu>, Paolo Zaffino <p.zaffino@unicz.it>
License-Expression: MIT
Project-URL: Homepage, https://github.com/ciroraggio/AugmentedDataLoader
Project-URL: Issues, https://github.com/ciroraggio/AugmentedDataLoader/issues
Classifier: Programming Language :: Python :: 3
Classifier: Operating System :: OS Independent
Requires-Python: >=3.9
License-File: LICENSE.txt
Requires-Dist: monai
Requires-Dist: torch
Requires-Dist: matplotlib
Dynamic: author
Dynamic: home-page
Dynamic: license-file
Dynamic: requires-python
